botanical/__init__.py
botanical/_license/licenses/gpl-3.0-standalone.html
botanical/business/business.r.html
botanical/business/decorators/examples/example_1.py
botanical/business/decorators/examples/multiple.py
botanical/cadence/UTC/current.py
botanical/cadence/UTC/status_current.py
botanical/cadence/UTC/leap/seconds.py
botanical/cadence/UTC/leap/years.py
botanical/cadence/UTC/month/strings.py
botanical/cadence/orbits/orbits.r.html
botanical/cycle/__init__.py
botanical/cycle/loops/__init__.py
botanical/cycle/loops/loops.r.html
botanical/cycle/loops/status_2.py
botanical/cycle/loops/status_3.py
botanical/cycle/loops/status_4.py
botanical/cycle/params/__init__.py
botanical/cycle/params/status_1.py
botanical/cycle/params/status_2.py
botanical/cycle/params_2/__init__.py
botanical/cycle/params_2/status_1.py
botanical/cycle/presents/__init__.py
botanical/flow/flow.r.html
botanical/flow/demux_mux/__init__.py
botanical/flow/demux_mux/demux_mux.r.html
botanical/flow/demux_mux/_status/status_1.py
botanical/insure/equalities.py
botanical/insure/equality.py
botanical/insure/status_equalitites_1.py
botanical/modules/exceptions/parse.py
botanical/modules/fasten/__init__.py
botanical/modules/fasten/_status/example.py
botanical/modules/fasten/_status/example_caller.py
botanical/modules/fasten/_status/status_1.py
botanical/modules/string/end_of_string_is.py
"botanical/paths/fs, rsync details.r.html"
"botanical/paths/fs, rsync.r.html"
botanical/paths/fs.r.html
botanical/paths/directory/directory.html
botanical/paths/directory/DEALLOCATE/__init__.py
botanical/paths/directory/EQUALIZE/__init__.py
botanical/paths/directory/EQUALIZE/STATUS_1/STATUS_1.py
botanical/paths/directory/EQUALIZE/STATUS_1/START/1/1.py
botanical/paths/directory/EQUALIZE/STATUS_2/STATUS_1.py
botanical/paths/directory/EQUALIZE/STATUS_2/START/1/1.py
botanical/paths/directory/RSYNC/__init__.py
botanical/paths/directory/SIZE/__init__.py
botanical/paths/directory/SIZE/STATUS/STATUS_1.py
botanical-1.0.0.dist-info/METADATA
botanical-1.0.0.dist-info/WHEEL
botanical-1.0.0.dist-info/top_level.txt
botanical-1.0.0.dist-info/RECORD
