Metadata-Version: 2.1
Name: botanical
Version: 1.0.0
Summary: various botanical tools
License: GPL 3.0
Requires-Dist: psutil
